gbp_ps-1.8.0.dist-info/METADATA
gbp_ps-1.8.0.dist-info/WHEEL
gbp_ps-1.8.0.dist-info/entry_points.txt
gbp_ps-1.8.0.dist-info/licenses/LICENSE
gbp_ps/__init__.py
gbp_ps/assets/bashrc-local.bash
gbp_ps/assets/bashrc.bash
gbp_ps/cli/__init__.py
gbp_ps/cli/add_process.py
gbp_ps/cli/dump_bashrc.py
gbp_ps/cli/ps.py
gbp_ps/django/__init__.py
gbp_ps/django/gbp_ps/__init__.py
gbp_ps/django/gbp_ps/apps.py
gbp_ps/django/gbp_ps/migrations/0001_initial.py
gbp_ps/django/gbp_ps/migrations/0001_squashed_0002_alter_buildprocess_phase.py
gbp_ps/django/gbp_ps/migrations/0002_alter_buildprocess_phase.py
gbp_ps/django/gbp_ps/migrations/__init__.py
gbp_ps/django/gbp_ps/models.py
gbp_ps/django/gbp_ps/static/gbp_ps/ps.css
gbp_ps/django/gbp_ps/static/gbp_ps/ps.js
gbp_ps/django/gbp_ps/templates/gbp_ps/ps/main.html
gbp_ps/django/gbp_ps/templates/gentoo_build_publisher/base.html
gbp_ps/django/gbp_ps/views.py
gbp_ps/exceptions.py
gbp_ps/graphql/__init__.py
gbp_ps/graphql/build_process.py
gbp_ps/graphql/mutations.py
gbp_ps/graphql/queries.py
gbp_ps/graphql/schema.graphql
gbp_ps/py.typed
gbp_ps/queries/add_process.graphql
gbp_ps/queries/get_processes.graphql
gbp_ps/repository/__init__.py
gbp_ps/repository/django.py
gbp_ps/repository/redis.py
gbp_ps/repository/sqlite.py
gbp_ps/settings.py
gbp_ps/signals.py
gbp_ps/types.py
gbp_ps/utils.py
gbp_ps-1.8.0.dist-info/RECORD
