Metadata-Version: 2.1
Name: gbp-ps
Version: 1.8.0
Summary: Store and report GBP build status
Author-Email: Albert Hopkins <marduk@letterboxes.org>
License: GPL3+
Classifier: Environment :: Console
Classifier: License :: OSI Approved :: GNU General Public License v3 or later (GPLv3+)
Classifier: Operating System :: POSIX :: Linux
Classifier: Topic :: System :: Software Distribution
Classifier: Programming Language :: Python :: 3
Project-URL: homepage, https://github.com/enku/gbp-ps
Project-URL: repository, https://github.com/enku/gbp-ps
Requires-Python: >=3.12
Requires-Dist: gbpcli>=2.4.0
Requires-Dist: rich>=13.6.0
Provides-Extra: server
Requires-Dist: ariadne>=0.21; extra == "server"
Requires-Dist: gentoo-build-publisher>=3.1.0; extra == "server"
Provides-Extra: redis
Requires-Dist: gbp-ps[server]; extra == "redis"
Requires-Dist: redis[hiredis]>=5.0.1; extra == "redis"
Requires-Dist: ormsgpack>=1.9.0; extra == "redis"
Provides-Extra: all
Requires-Dist: gbp-ps[redis,server]; extra == "all"
